tube_search/__init__.py
tube_search/video.py
tube_search-0.0.2.1.dist-info/licenses/LICENSE
tube_search-0.0.2.1.dist-info/METADATA
tube_search-0.0.2.1.dist-info/WHEEL
tube_search-0.0.2.1.dist-info/top_level.txt
tube_search-0.0.2.1.dist-info/RECORD
