Metadata-Version: 2.4
Name: tube-search
Version: 0.0.2.1
Summary: 🔎 Search for videos, channels and playlists on YouTube quickly and easily.
Author: BubbalooTeam
Author-email: bubbalooteam@proton.me
License: MIT License
Keywords: tube search,tube_search
License-File: LICENSE
Requires-Dist: httpx[http2]
Dynamic: author
Dynamic: author-email
Dynamic: description
Dynamic: description-content-type
Dynamic: keywords
Dynamic: license
Dynamic: license-file
Dynamic: requires-dist
Dynamic: summary
